[{"TIME":1209686400000,"MATURITY":2,"Value":3.91},{"TIME":1209686400000,"MATURITY":3,"Value":3.92},{"TIME":1209686400000,"MATURITY":4,"Value":3.96},{"TIME":1209686400000,"MATURITY":5,"Value":4.01},{"TIME":1209686400000,"MATURITY":6,"Value":4.08},{"TIME":1209686400000,"MATURITY":7,"Value":4.16},{"TIME":1209686400000,"MATURITY":8,"Value":4.23},{"TIME":1209686400000,"MATURITY":9,"Value":4.3},{"TIME":1209686400000,"MATURITY":10,"Value":4.36},{"TIME":1209945600000,"MATURITY":2,"Value":3.9},{"TIME":1209945600000,"MATURITY":3,"Value":3.89},{"TIME":1209945600000,"MATURITY":4,"Value":3.93},{"TIME":1209945600000,"MATURITY":5,"Value":3.98},{"TIME":1209945600000,"MATURITY":6,"Value":4.05},{"TIME":1209945600000,"MATURITY":7,"Value":4.13},{"TIME":1209945600000,"MATURITY":8,"Value":4.2},{"TIME":1209945600000,"MATURITY":9,"Value":4.27},{"TIME":1209945600000,"MATURITY":10,"Value":4.34},{"TIME":1210032000000,"MATURITY":2,"Value":3.81},{"TIME":1210032000000,"MATURITY":3,"Value":3.8},{"TIME":1210032000000,"MATURITY":4,"Value":3.84},{"TIME":1210032000000,"MATURITY":5,"Value":3.91},{"TIME":1210032000000,"MATURITY":6,"Value":3.99},{"TIME":1210032000000,"MATURITY":7,"Value":4.07},{"TIME":1210032000000,"MATURITY":8,"Value":4.15},{"TIME":1210032000000,"MATURITY":9,"Value":4.23},{"TIME":1210032000000,"MATURITY":10,"Value":4.3},{"TIME":1210118400000,"MATURITY":2,"Value":3.84},{"TIME":1210118400000,"MATURITY":3,"Value":3.84},{"TIME":1210118400000,"MATURITY":4,"Value":3.89},{"TIME":1210118400000,"MATURITY":5,"Value":3.96},{"TIME":1210118400000,"MATURITY":6,"Value":4.04},{"TIME":1210118400000,"MATURITY":7,"Value":4.13},{"TIME":1210118400000,"MATURITY":8,"Value":4.21},{"TIME":1210118400000,"MATURITY":9,"Value":4.29},{"TIME":1210118400000,"MATURITY":10,"Value":4.35},{"TIME":1210204800000,"MATURITY":2,"Value":3.8},{"TIME":1210204800000,"MATURITY":3,"Value":3.78},{"TIME":1210204800000,"MATURITY":4,"Value":3.82},{"TIME":1210204800000,"MATURITY":5,"Value":3.89},{"TIME":1210204800000,"MATURITY":6,"Value":3.97},{"TIME":1210204800000,"MATURITY":7,"Value":4.06},{"TIME":1210204800000,"MATURITY":8,"Value":4.15},{"TIME":1210204800000,"MATURITY":9,"Value":4.22},{"TIME":1210204800000,"MATURITY":10,"Value":4.29},{"TIME":1210291200000,"MATURITY":2,"Value":3.74},{"TIME":1210291200000,"MATURITY":3,"Value":3.7},{"TIME":1210291200000,"MATURITY":4,"Value":3.73},{"TIME":1210291200000,"MATURITY":5,"Value":3.8},{"TIME":1210291200000,"MATURITY":6,"Value":3.89},{"TIME":1210291200000,"MATURITY":7,"Value":3.99},{"TIME":1210291200000,"MATURITY":8,"Value":4.08},{"TIME":1210291200000,"MATURITY":9,"Value":4.15},{"TIME":1210291200000,"MATURITY":10,"Value":4.22},{"TIME":1210550400000,"MATURITY":2,"Value":3.79},{"TIME":1210550400000,"MATURITY":3,"Value":3.76},{"TIME":1210550400000,"MATURITY":4,"Value":3.78},{"TIME":1210550400000,"MATURITY":5,"Value":3.83},{"TIME":1210550400000,"MATURITY":6,"Value":3.91},{"TIME":1210550400000,"MATURITY":7,"Value":3.99},{"TIME":1210550400000,"MATURITY":8,"Value":4.08},{"TIME":1210550400000,"MATURITY":9,"Value":4.15},{"TIME":1210550400000,"MATURITY":10,"Value":4.22},{"TIME":1210636800000,"MATURITY":2,"Value":3.89},{"TIME":1210636800000,"MATURITY":3,"Value":3.86},{"TIME":1210636800000,"MATURITY":4,"Value":3.87},{"TIME":1210636800000,"MATURITY":5,"Value":3.92},{"TIME":1210636800000,"MATURITY":6,"Value":3.99},{"TIME":1210636800000,"MATURITY":7,"Value":4.07},{"TIME":1210636800000,"MATURITY":8,"Value":4.15},{"TIME":1210636800000,"MATURITY":9,"Value":4.22},{"TIME":1210636800000,"MATURITY":10,"Value":4.29},{"TIME":1210723200000,"MATURITY":2,"Value":3.95},{"TIME":1210723200000,"MATURITY":3,"Value":3.93},{"TIME":1210723200000,"MATURITY":4,"Value":3.94},{"TIME":1210723200000,"MATURITY":5,"Value":3.98},{"TIME":1210723200000,"MATURITY":6,"Value":4.04},{"TIME":1210723200000,"MATURITY":7,"Value":4.11},{"TIME":1210723200000,"MATURITY":8,"Value":4.19},{"TIME":1210723200000,"MATURITY":9,"Value":4.26},{"TIME":1210723200000,"MATURITY":10,"Value":4.33},{"TIME":1210809600000,"MATURITY":2,"Value":4.02},{"TIME":1210809600000,"MATURITY":3,"Value":4.0},{"TIME":1210809600000,"MATURITY":4,"Value":4.01},{"TIME":1210809600000,"MATURITY":5,"Value":4.05},{"TIME":1210809600000,"MATURITY":6,"Value":4.11},{"TIME":1210809600000,"MATURITY":7,"Value":4.18},{"TIME":1210809600000,"MATURITY":8,"Value":4.25},{"TIME":1210809600000,"MATURITY":9,"Value":4.32},{"TIME":1210809600000,"MATURITY":10,"Value":4.39},{"TIME":1210896000000,"MATURITY":2,"Value":4.03},{"TIME":1210896000000,"MATURITY":3,"Value":4.02},{"TIME":1210896000000,"MATURITY":4,"Value":4.02},{"TIME":1210896000000,"MATURITY":5,"Value":4.05},{"TIME":1210896000000,"MATURITY":6,"Value":4.1},{"TIME":1210896000000,"MATURITY":7,"Value":4.16},{"TIME":1210896000000,"MATURITY":8,"Value":4.23},{"TIME":1210896000000,"MATURITY":9,"Value":4.29},{"TIME":1210896000000,"MATURITY":10,"Value":4.35},{"TIME":1211155200000,"MATURITY":2,"Value":4.02},{"TIME":1211155200000,"MATURITY":3,"Value":4.0},{"TIME":1211155200000,"MATURITY":4,"Value":4.01},{"TIME":1211155200000,"MATURITY":5,"Value":4.04},{"TIME":1211155200000,"MATURITY":6,"Value":4.09},{"TIME":1211155200000,"MATURITY":7,"Value":4.16},{"TIME":1211155200000,"MATURITY":8,"Value":4.22},{"TIME":1211155200000,"MATURITY":9,"Value":4.29},{"TIME":1211155200000,"MATURITY":10,"Value":4.35},{"TIME":1211241600000,"MATURITY":2,"Value":4.03},{"TIME":1211241600000,"MATURITY":3,"Value":4.02},{"TIME":1211241600000,"MATURITY":4,"Value":4.02},{"TIME":1211241600000,"MATURITY":5,"Value":4.05},{"TIME":1211241600000,"MATURITY":6,"Value":4.1},{"TIME":1211241600000,"MATURITY":7,"Value":4.16},{"TIME":1211241600000,"MATURITY":8,"Value":4.22},{"TIME":1211241600000,"MATURITY":9,"Value":4.29},{"TIME":1211241600000,"MATURITY":10,"Value":4.35},{"TIME":1211328000000,"MATURITY":2,"Value":4.12},{"TIME":1211328000000,"MATURITY":3,"Value":4.11},{"TIME":1211328000000,"MATURITY":4,"Value":4.1},{"TIME":1211328000000,"MATURITY":5,"Value":4.12},{"TIME":1211328000000,"MATURITY":6,"Value":4.17},{"TIME":1211328000000,"MATURITY":7,"Value":4.22},{"TIME":1211328000000,"MATURITY":8,"Value":4.28},{"TIME":1211328000000,"MATURITY":9,"Value":4.34},{"TIME":1211328000000,"MATURITY":10,"Value":4.4},{"TIME":1211414400000,"MATURITY":2,"Value":4.18},{"TIME":1211414400000,"MATURITY":3,"Value":4.16},{"TIME":1211414400000,"MATURITY":4,"Value":4.15},{"TIME":1211414400000,"MATURITY":5,"Value":4.17},{"TIME":1211414400000,"MATURITY":6,"Value":4.2},{"TIME":1211414400000,"MATURITY":7,"Value":4.26},{"TIME":1211414400000,"MATURITY":8,"Value":4.31},{"TIME":1211414400000,"MATURITY":9,"Value":4.37},{"TIME":1211414400000,"MATURITY":10,"Value":4.43},{"TIME":1211500800000,"MATURITY":2,"Value":4.2},{"TIME":1211500800000,"MATURITY":3,"Value":4.17},{"TIME":1211500800000,"MATURITY":4,"Value":4.15},{"TIME":1211500800000,"MATURITY":5,"Value":4.15},{"TIME":1211500800000,"MATURITY":6,"Value":4.18},{"TIME":1211500800000,"MATURITY":7,"Value":4.23},{"TIME":1211500800000,"MATURITY":8,"Value":4.28},{"TIME":1211500800000,"MATURITY":9,"Value":4.34},{"TIME":1211500800000,"MATURITY":10,"Value":4.39},{"TIME":1211760000000,"MATURITY":2,"Value":4.2},{"TIME":1211760000000,"MATURITY":3,"Value":4.18},{"TIME":1211760000000,"MATURITY":4,"Value":4.16},{"TIME":1211760000000,"MATURITY":5,"Value":4.17},{"TIME":1211760000000,"MATURITY":6,"Value":4.2},{"TIME":1211760000000,"MATURITY":7,"Value":4.25},{"TIME":1211760000000,"MATURITY":8,"Value":4.3},{"TIME":1211760000000,"MATURITY":9,"Value":4.36},{"TIME":1211760000000,"MATURITY":10,"Value":4.42},{"TIME":1211846400000,"MATURITY":2,"Value":4.2},{"TIME":1211846400000,"MATURITY":3,"Value":4.17},{"TIME":1211846400000,"MATURITY":4,"Value":4.16},{"TIME":1211846400000,"MATURITY":5,"Value":4.18},{"TIME":1211846400000,"MATURITY":6,"Value":4.21},{"TIME":1211846400000,"MATURITY":7,"Value":4.26},{"TIME":1211846400000,"MATURITY":8,"Value":4.32},{"TIME":1211846400000,"MATURITY":9,"Value":4.38},{"TIME":1211846400000,"MATURITY":10,"Value":4.43},{"TIME":1211932800000,"MATURITY":2,"Value":4.22},{"TIME":1211932800000,"MATURITY":3,"Value":4.21},{"TIME":1211932800000,"MATURITY":4,"Value":4.21},{"TIME":1211932800000,"MATURITY":5,"Value":4.22},{"TIME":1211932800000,"MATURITY":6,"Value":4.26},{"TIME":1211932800000,"MATURITY":7,"Value":4.31},{"TIME":1211932800000,"MATURITY":8,"Value":4.36},{"TIME":1211932800000,"MATURITY":9,"Value":4.42},{"TIME":1211932800000,"MATURITY":10,"Value":4.48},{"TIME":1212019200000,"MATURITY":2,"Value":4.31},{"TIME":1212019200000,"MATURITY":3,"Value":4.31},{"TIME":1212019200000,"MATURITY":4,"Value":4.3},{"TIME":1212019200000,"MATURITY":5,"Value":4.32},{"TIME":1212019200000,"MATURITY":6,"Value":4.35},{"TIME":1212019200000,"MATURITY":7,"Value":4.4},{"TIME":1212019200000,"MATURITY":8,"Value":4.46},{"TIME":1212019200000,"MATURITY":9,"Value":4.51},{"TIME":1212019200000,"MATURITY":10,"Value":4.57},{"TIME":1212105600000,"MATURITY":2,"Value":4.28},{"TIME":1212105600000,"MATURITY":3,"Value":4.26},{"TIME":1212105600000,"MATURITY":4,"Value":4.25},{"TIME":1212105600000,"MATURITY":5,"Value":4.27},{"TIME":1212105600000,"MATURITY":6,"Value":4.3},{"TIME":1212105600000,"MATURITY":7,"Value":4.35},{"TIME":1212105600000,"MATURITY":8,"Value":4.41},{"TIME":1212105600000,"MATURITY":9,"Value":4.47},{"TIME":1212105600000,"MATURITY":10,"Value":4.52}]