[{"TIME":1241395200000,"MATURITY":2,"Value":1.52},{"TIME":1241395200000,"MATURITY":3,"Value":2.0},{"TIME":1241395200000,"MATURITY":4,"Value":2.4},{"TIME":1241395200000,"MATURITY":5,"Value":2.73},{"TIME":1241395200000,"MATURITY":6,"Value":3.01},{"TIME":1241395200000,"MATURITY":7,"Value":3.26},{"TIME":1241395200000,"MATURITY":8,"Value":3.47},{"TIME":1241395200000,"MATURITY":9,"Value":3.65},{"TIME":1241395200000,"MATURITY":10,"Value":3.81},{"TIME":1241481600000,"MATURITY":2,"Value":1.52},{"TIME":1241481600000,"MATURITY":3,"Value":2.0},{"TIME":1241481600000,"MATURITY":4,"Value":2.39},{"TIME":1241481600000,"MATURITY":5,"Value":2.72},{"TIME":1241481600000,"MATURITY":6,"Value":3.0},{"TIME":1241481600000,"MATURITY":7,"Value":3.25},{"TIME":1241481600000,"MATURITY":8,"Value":3.46},{"TIME":1241481600000,"MATURITY":9,"Value":3.64},{"TIME":1241481600000,"MATURITY":10,"Value":3.79},{"TIME":1241568000000,"MATURITY":2,"Value":1.49},{"TIME":1241568000000,"MATURITY":3,"Value":1.98},{"TIME":1241568000000,"MATURITY":4,"Value":2.37},{"TIME":1241568000000,"MATURITY":5,"Value":2.71},{"TIME":1241568000000,"MATURITY":6,"Value":3.0},{"TIME":1241568000000,"MATURITY":7,"Value":3.25},{"TIME":1241568000000,"MATURITY":8,"Value":3.46},{"TIME":1241568000000,"MATURITY":9,"Value":3.64},{"TIME":1241568000000,"MATURITY":10,"Value":3.8},{"TIME":1241654400000,"MATURITY":2,"Value":1.55},{"TIME":1241654400000,"MATURITY":3,"Value":2.06},{"TIME":1241654400000,"MATURITY":4,"Value":2.48},{"TIME":1241654400000,"MATURITY":5,"Value":2.82},{"TIME":1241654400000,"MATURITY":6,"Value":3.12},{"TIME":1241654400000,"MATURITY":7,"Value":3.37},{"TIME":1241654400000,"MATURITY":8,"Value":3.59},{"TIME":1241654400000,"MATURITY":9,"Value":3.77},{"TIME":1241654400000,"MATURITY":10,"Value":3.93},{"TIME":1241740800000,"MATURITY":2,"Value":1.47},{"TIME":1241740800000,"MATURITY":3,"Value":2.0},{"TIME":1241740800000,"MATURITY":4,"Value":2.44},{"TIME":1241740800000,"MATURITY":5,"Value":2.8},{"TIME":1241740800000,"MATURITY":6,"Value":3.11},{"TIME":1241740800000,"MATURITY":7,"Value":3.37},{"TIME":1241740800000,"MATURITY":8,"Value":3.6},{"TIME":1241740800000,"MATURITY":9,"Value":3.79},{"TIME":1241740800000,"MATURITY":10,"Value":3.96},{"TIME":1242000000000,"MATURITY":2,"Value":1.45},{"TIME":1242000000000,"MATURITY":3,"Value":1.97},{"TIME":1242000000000,"MATURITY":4,"Value":2.39},{"TIME":1242000000000,"MATURITY":5,"Value":2.75},{"TIME":1242000000000,"MATURITY":6,"Value":3.05},{"TIME":1242000000000,"MATURITY":7,"Value":3.31},{"TIME":1242000000000,"MATURITY":8,"Value":3.54},{"TIME":1242000000000,"MATURITY":9,"Value":3.73},{"TIME":1242000000000,"MATURITY":10,"Value":3.9},{"TIME":1242086400000,"MATURITY":2,"Value":1.49},{"TIME":1242086400000,"MATURITY":3,"Value":2.01},{"TIME":1242086400000,"MATURITY":4,"Value":2.43},{"TIME":1242086400000,"MATURITY":5,"Value":2.79},{"TIME":1242086400000,"MATURITY":6,"Value":3.09},{"TIME":1242086400000,"MATURITY":7,"Value":3.35},{"TIME":1242086400000,"MATURITY":8,"Value":3.57},{"TIME":1242086400000,"MATURITY":9,"Value":3.77},{"TIME":1242086400000,"MATURITY":10,"Value":3.93},{"TIME":1242172800000,"MATURITY":2,"Value":1.41},{"TIME":1242172800000,"MATURITY":3,"Value":1.92},{"TIME":1242172800000,"MATURITY":4,"Value":2.35},{"TIME":1242172800000,"MATURITY":5,"Value":2.71},{"TIME":1242172800000,"MATURITY":6,"Value":3.01},{"TIME":1242172800000,"MATURITY":7,"Value":3.28},{"TIME":1242172800000,"MATURITY":8,"Value":3.51},{"TIME":1242172800000,"MATURITY":9,"Value":3.71},{"TIME":1242172800000,"MATURITY":10,"Value":3.88},{"TIME":1242259200000,"MATURITY":2,"Value":1.42},{"TIME":1242259200000,"MATURITY":3,"Value":1.93},{"TIME":1242259200000,"MATURITY":4,"Value":2.35},{"TIME":1242259200000,"MATURITY":5,"Value":2.71},{"TIME":1242259200000,"MATURITY":6,"Value":3.02},{"TIME":1242259200000,"MATURITY":7,"Value":3.29},{"TIME":1242259200000,"MATURITY":8,"Value":3.52},{"TIME":1242259200000,"MATURITY":9,"Value":3.72},{"TIME":1242259200000,"MATURITY":10,"Value":3.89},{"TIME":1242345600000,"MATURITY":2,"Value":1.41},{"TIME":1242345600000,"MATURITY":3,"Value":1.94},{"TIME":1242345600000,"MATURITY":4,"Value":2.38},{"TIME":1242345600000,"MATURITY":5,"Value":2.74},{"TIME":1242345600000,"MATURITY":6,"Value":3.06},{"TIME":1242345600000,"MATURITY":7,"Value":3.33},{"TIME":1242345600000,"MATURITY":8,"Value":3.56},{"TIME":1242345600000,"MATURITY":9,"Value":3.76},{"TIME":1242345600000,"MATURITY":10,"Value":3.93},{"TIME":1242604800000,"MATURITY":2,"Value":1.39},{"TIME":1242604800000,"MATURITY":3,"Value":1.92},{"TIME":1242604800000,"MATURITY":4,"Value":2.36},{"TIME":1242604800000,"MATURITY":5,"Value":2.73},{"TIME":1242604800000,"MATURITY":6,"Value":3.05},{"TIME":1242604800000,"MATURITY":7,"Value":3.32},{"TIME":1242604800000,"MATURITY":8,"Value":3.55},{"TIME":1242604800000,"MATURITY":9,"Value":3.75},{"TIME":1242604800000,"MATURITY":10,"Value":3.92},{"TIME":1242691200000,"MATURITY":2,"Value":1.44},{"TIME":1242691200000,"MATURITY":3,"Value":1.98},{"TIME":1242691200000,"MATURITY":4,"Value":2.42},{"TIME":1242691200000,"MATURITY":5,"Value":2.8},{"TIME":1242691200000,"MATURITY":6,"Value":3.12},{"TIME":1242691200000,"MATURITY":7,"Value":3.39},{"TIME":1242691200000,"MATURITY":8,"Value":3.62},{"TIME":1242691200000,"MATURITY":9,"Value":3.82},{"TIME":1242691200000,"MATURITY":10,"Value":3.99},{"TIME":1242777600000,"MATURITY":2,"Value":1.51},{"TIME":1242777600000,"MATURITY":3,"Value":2.03},{"TIME":1242777600000,"MATURITY":4,"Value":2.46},{"TIME":1242777600000,"MATURITY":5,"Value":2.82},{"TIME":1242777600000,"MATURITY":6,"Value":3.13},{"TIME":1242777600000,"MATURITY":7,"Value":3.39},{"TIME":1242777600000,"MATURITY":8,"Value":3.62},{"TIME":1242777600000,"MATURITY":9,"Value":3.82},{"TIME":1242777600000,"MATURITY":10,"Value":3.98},{"TIME":1242864000000,"MATURITY":2,"Value":1.45},{"TIME":1242864000000,"MATURITY":3,"Value":1.96},{"TIME":1242864000000,"MATURITY":4,"Value":2.4},{"TIME":1242864000000,"MATURITY":5,"Value":2.77},{"TIME":1242864000000,"MATURITY":6,"Value":3.08},{"TIME":1242864000000,"MATURITY":7,"Value":3.34},{"TIME":1242864000000,"MATURITY":8,"Value":3.57},{"TIME":1242864000000,"MATURITY":9,"Value":3.77},{"TIME":1242864000000,"MATURITY":10,"Value":3.94},{"TIME":1242950400000,"MATURITY":2,"Value":1.48},{"TIME":1242950400000,"MATURITY":3,"Value":2.01},{"TIME":1242950400000,"MATURITY":4,"Value":2.46},{"TIME":1242950400000,"MATURITY":5,"Value":2.84},{"TIME":1242950400000,"MATURITY":6,"Value":3.16},{"TIME":1242950400000,"MATURITY":7,"Value":3.43},{"TIME":1242950400000,"MATURITY":8,"Value":3.66},{"TIME":1242950400000,"MATURITY":9,"Value":3.87},{"TIME":1242950400000,"MATURITY":10,"Value":4.04},{"TIME":1243209600000,"MATURITY":2,"Value":1.6},{"TIME":1243209600000,"MATURITY":3,"Value":2.14},{"TIME":1243209600000,"MATURITY":4,"Value":2.57},{"TIME":1243209600000,"MATURITY":5,"Value":2.93},{"TIME":1243209600000,"MATURITY":6,"Value":3.24},{"TIME":1243209600000,"MATURITY":7,"Value":3.51},{"TIME":1243209600000,"MATURITY":8,"Value":3.73},{"TIME":1243209600000,"MATURITY":9,"Value":3.93},{"TIME":1243209600000,"MATURITY":10,"Value":4.1},{"TIME":1243296000000,"MATURITY":2,"Value":1.57},{"TIME":1243296000000,"MATURITY":3,"Value":2.12},{"TIME":1243296000000,"MATURITY":4,"Value":2.58},{"TIME":1243296000000,"MATURITY":5,"Value":2.95},{"TIME":1243296000000,"MATURITY":6,"Value":3.25},{"TIME":1243296000000,"MATURITY":7,"Value":3.51},{"TIME":1243296000000,"MATURITY":8,"Value":3.73},{"TIME":1243296000000,"MATURITY":9,"Value":3.92},{"TIME":1243296000000,"MATURITY":10,"Value":4.07},{"TIME":1243382400000,"MATURITY":2,"Value":1.6},{"TIME":1243382400000,"MATURITY":3,"Value":2.16},{"TIME":1243382400000,"MATURITY":4,"Value":2.62},{"TIME":1243382400000,"MATURITY":5,"Value":3.0},{"TIME":1243382400000,"MATURITY":6,"Value":3.31},{"TIME":1243382400000,"MATURITY":7,"Value":3.57},{"TIME":1243382400000,"MATURITY":8,"Value":3.79},{"TIME":1243382400000,"MATURITY":9,"Value":3.97},{"TIME":1243382400000,"MATURITY":10,"Value":4.13},{"TIME":1243468800000,"MATURITY":2,"Value":1.59},{"TIME":1243468800000,"MATURITY":3,"Value":2.17},{"TIME":1243468800000,"MATURITY":4,"Value":2.64},{"TIME":1243468800000,"MATURITY":5,"Value":3.02},{"TIME":1243468800000,"MATURITY":6,"Value":3.34},{"TIME":1243468800000,"MATURITY":7,"Value":3.61},{"TIME":1243468800000,"MATURITY":8,"Value":3.83},{"TIME":1243468800000,"MATURITY":9,"Value":4.02},{"TIME":1243468800000,"MATURITY":10,"Value":4.18},{"TIME":1243555200000,"MATURITY":2,"Value":1.53},{"TIME":1243555200000,"MATURITY":3,"Value":2.11},{"TIME":1243555200000,"MATURITY":4,"Value":2.6},{"TIME":1243555200000,"MATURITY":5,"Value":3.0},{"TIME":1243555200000,"MATURITY":6,"Value":3.33},{"TIME":1243555200000,"MATURITY":7,"Value":3.6},{"TIME":1243555200000,"MATURITY":8,"Value":3.83},{"TIME":1243555200000,"MATURITY":9,"Value":4.02},{"TIME":1243555200000,"MATURITY":10,"Value":4.18}]